MANIFEST.in
setup.cfg
setup.py
django_quick_reports.egg-info/PKG-INFO
django_quick_reports.egg-info/SOURCES.txt
django_quick_reports.egg-info/dependency_links.txt
django_quick_reports.egg-info/requires.txt
django_quick_reports.egg-info/top_level.txt
quick_reports/__init__.py
quick_reports/admin.py
quick_reports/apps.py
quick_reports/models.py
quick_reports/sites.py
quick_reports/tests.py
quick_reports/urls.py
quick_reports/views.py
quick_reports/api/__init__.py
quick_reports/api/admin.py
quick_reports/api/models.py
quick_reports/api/serializers.py
quick_reports/api/tests.py
quick_reports/api/urls.py
quick_reports/api/views.py
quick_reports/api/migrations/__init__.py
quick_reports/migrations/__init__.py
quick_reports/static/quick_reports/bower.json
quick_reports/static/quick_reports/bower_components/angular/.bower.json
quick_reports/static/quick_reports/bower_components/angular/README.md
quick_reports/static/quick_reports/bower_components/angular/angular-csp.css
quick_reports/static/quick_reports/bower_components/angular/angular.js
quick_reports/static/quick_reports/bower_components/angular/angular.min.js
quick_reports/static/quick_reports/bower_components/angular/angular.min.js.gzip
quick_reports/static/quick_reports/bower_components/angular/angular.min.js.map
quick_reports/static/quick_reports/bower_components/angular/bower.json
quick_reports/static/quick_reports/bower_components/angular/index.js
quick_reports/static/quick_reports/bower_components/angular/package.json
quick_reports/static/quick_reports/bower_components/angular-flot/.bower.json
quick_reports/static/quick_reports/bower_components/angular-flot/.gitignore
quick_reports/static/quick_reports/bower_components/angular-flot/AUTHORS
quick_reports/static/quick_reports/bower_components/angular-flot/CHANGELOG.md
quick_reports/static/quick_reports/bower_components/angular-flot/CONTRIBUTING.md
quick_reports/static/quick_reports/bower_components/angular-flot/LICENSE.txt
quick_reports/static/quick_reports/bower_components/angular-flot/README.md
quick_reports/static/quick_reports/bower_components/angular-flot/angular-flot.js
quick_reports/static/quick_reports/bower_components/angular-flot/bower.json
