Metadata-Version: 1.1
Name: django-quick-reports
Version: 0.1.1
Summary: Ready-to-use class-based django reports
Home-page: UNKNOWN
Author: Baris Bilgic
Author-email: baris@jooysoft.com
License: BSD
Keywords: django report
Platform: UNKNOWN
Classifier: Development Status :: 5 - Production/Stable
Classifier: Environment :: Web Environment
Classifier: Framework :: Django
Classifier: Programming Language :: Python
Classifier: Programming Language :: Python :: 2.7
Classifier: Intended Audience :: Developers
Classifier: Intended Audience :: System Administrators
Classifier: License :: OSI Approved :: BSD License
